LICENSE.md
README.md
setup.py
pelican_exporter/__init__.py
pelican_exporter/config_load.py
pelican_exporter/http_client.py
pelican_exporter/http_server.py
pelican_exporter/pelican_exporter.py
pelican_exporter.egg-info/PKG-INFO
pelican_exporter.egg-info/SOURCES.txt
pelican_exporter.egg-info/dependency_links.txt
pelican_exporter.egg-info/entry_points.txt
pelican_exporter.egg-info/requires.txt
pelican_exporter.egg-info/top_level.txt
pelican_exporter/dto/__init__.py
pelican_exporter/dto/config.py
pelican_exporter/dto/metrics.py
pelican_exporter/dto/validation.py
pelican_exporter/enum/__init__.py
pelican_exporter/enum/server_list_type.py
pelican_exporter/tests/__init__.py
pelican_exporter/tests/test_config_load.py
pelican_exporter/tests/test_http_server.py
pelican_exporter/tests/dto/__init__.py
pelican_exporter/tests/dto/test_config.py