Metadata-Version: 2.4
Name: pelican_exporter
Version: 0.1.2
Summary: Metrics exporter for pelican
Home-page: https://github.com/scarecr0w12/pelican_exporter
Author: Scarecr0w12
Author-email: jacob@thecorehosting.net
License: GPL-3
Requires-Python: >=3.11
License-File: LICENSE.md
Requires-Dist: PyYAML~=6.0.1
Requires-Dist: setuptools~=69.1.1
Requires-Dist: python-dateutil~=2.9.0.post0
Requires-Dist: prometheus_client~=0.20.0
Requires-Dist: dataclasses_json~=0.6.4
Requires-Dist: requests~=2.31
Dynamic: author
Dynamic: author-email
Dynamic: home-page
Dynamic: license
Dynamic: license-file
Dynamic: requires-dist
Dynamic: requires-python
Dynamic: summary
